[{"data_date":"2012-01-15","unix_timestamp":1326585600,"individuals":9500},
 {"data_date":"2012-02-29","unix_timestamp":1330473600,"individuals":10658},{"data_date":"2012-04-18","unix_timestamp":1334707200,"individuals":23955},{"data_date":"2012-04-23","unix_timestamp":1335139200,"individuals":23702},{"data_date":"2012-04-26","unix_timestamp":1335398400,"individuals":23343},{"data_date":"2012-05-02","unix_timestamp":1335916800,"individuals":23298},{"data_date":"2012-05-07","unix_timestamp":1336348800,"individuals":23011},{"data_date":"2012-05-21","unix_timestamp":1337558400,"individuals":22778},{"data_date":"2012-06-01","unix_timestamp":1338508800,"individuals":24433},{"data_date":"2012-06-04","unix_timestamp":1338768000,"individuals":26281},{"data_date":"2012-06-12","unix_timestamp":1339459200,"individuals":27405},{"data_date":"2012-06-22","unix_timestamp":1340323200,"individuals":32134},{"data_date":"2012-06-25","unix_timestamp":1340582400,"individuals":32380},{"data_date":"2012-06-26","unix_timestamp":1340668800,"individuals":33079},{"data_date":"2012-07-04","unix_timestamp":1341360000,"individuals":35099},{"data_date":"2012-07-05","unix_timestamp":1341446400,"individuals":35565},{"data_date":"2012-07-12","unix_timestamp":1342051200,"individuals":37353},{"data_date":"2012-07-20","unix_timestamp":1342742400,"individuals":42682},{"data_date":"2012-07-23","unix_timestamp":1343001600,"individuals":43387},{"data_date":"2012-07-31","unix_timestamp":1343692800,"individuals":44188},{"data_date":"2012-08-01","unix_timestamp":1343779200,"individuals":44038},{"data_date":"2012-08-08","unix_timestamp":1344384000,"individuals":46294},{"data_date":"2012-08-09","unix_timestamp":1344470400,"individuals":47053},{"data_date":"2012-08-10","unix_timestamp":1344556800,"individuals":50227},{"data_date":"2012-08-14","unix_timestamp":1344902400,"individuals":59710},{"data_date":"2012-08-15","unix_timestamp":1344988800,"individuals":61450},{"data_date":"2012-08-22","unix_timestamp":1345593600,"individuals":69828},{"data_date":"2012-08-23","unix_timestamp":1345680000,"individuals":74112},{"data_date":"2012-08-27","unix_timestamp":1346025600,"individuals":78409},{"data_date":"2012-08-30","unix_timestamp":1346284800,"individuals":80410},{"data_date":"2012-09-10","unix_timestamp":1347235200,"individuals":78431},{"data_date":"2012-09-12","unix_timestamp":1347408000,"individuals":80104},{"data_date":"2012-09-17","unix_timestamp":1347840000,"individuals":80177},{"data_date":"2012-09-20","unix_timestamp":1348099200,"individuals":83260},{"data_date":"2012-09-24","unix_timestamp":1348444800,"individuals":84084},{"data_date":"2012-09-27","unix_timestamp":1348704000,"individuals":87774},{"data_date":"2012-10-04","unix_timestamp":1349308800,"individuals":93576},{"data_date":"2012-10-08","unix_timestamp":1349654400,"individuals":96397},{"data_date":"2012-10-18","unix_timestamp":1350518400,"individuals":100363},{"data_date":"2012-10-22","unix_timestamp":1350864000,"individuals":101834},{"data_date":"2012-11-02","unix_timestamp":1351814400,"individuals":107769},{"data_date":"2012-11-05","unix_timestamp":1352073600,"individuals":110649},{"data_date":"2012-11-07","unix_timestamp":1352246400,"individuals":111890},{"data_date":"2012-11-12","unix_timestamp":1352678400,"individuals":112883},{"data_date":"2012-11-14","unix_timestamp":1352851200,"individuals":114944},{"data_date":"2012-11-19","unix_timestamp":1353283200,"individuals":120147},{"data_date":"2012-11-26","unix_timestamp":1353888000,"individuals":123747},{"data_date":"2012-12-06","unix_timestamp":1354752000,"individuals":135519},{"data_date":"2012-12-10","unix_timestamp":1355097600,"individuals":136319},{"data_date":"2012-12-11","unix_timestamp":1355184000,"individuals":136810},{"data_date":"2012-12-13","unix_timestamp":1355356800,"individuals":137756},{"data_date":"2012-12-17","unix_timestamp":1355702400,"individuals":141240},{"data_date":"2012-12-21","unix_timestamp":1356048000,"individuals":142670},{"data_date":"2012-12-24","unix_timestamp":1356307200,"individuals":144755},{"data_date":"2013-01-01","unix_timestamp":1356998400,"individuals":148441},{"data_date":"2013-01-06","unix_timestamp":1357430400,"individuals":150906},{"data_date":"2013-01-14","unix_timestamp":1358121600,"individuals":153307},{"data_date":"2013-01-16","unix_timestamp":1358294400,"individuals":154705},{"data_date":"2013-01-22","unix_timestamp":1358812800,"individuals":156801},{"data_date":"2013-01-28","unix_timestamp":1359331200,"individuals":163161},{"data_date":"2013-02-04","unix_timestamp":1359936000,"individuals":170643},{"data_date":"2013-02-05","unix_timestamp":1360022400,"individuals":170700},{"data_date":"2013-02-06","unix_timestamp":1360108800,"individuals":177180},{"data_date":"2013-02-07","unix_timestamp":1360195200,"individuals":177914},{"data_date":"2013-02-11","unix_timestamp":1360540800,"individuals":177387},{"data_date":"2013-02-13","unix_timestamp":1360713600,"individuals":180373},{"data_date":"2013-02-14","unix_timestamp":1360800000,"individuals":181729},{"data_date":"2013-02-15","unix_timestamp":1360886400,"individuals":182621},{"data_date":"2013-02-25","unix_timestamp":1361750400,"individuals":183846},{"data_date":"2013-02-26","unix_timestamp":1361836800,"individuals":184513},{"data_date":"2013-02-27","unix_timestamp":1361923200,"individuals":184585},{"data_date":"2013-03-01","unix_timestamp":1362096000,"individuals":185205},{"data_date":"2013-03-05","unix_timestamp":1362441600,"individuals":185982},{"data_date":"2013-03-09","unix_timestamp":1362787200,"individuals":258200},{"data_date":"2013-03-15","unix_timestamp":1363305600,"individuals":260341},{"data_date":"2013-03-18","unix_timestamp":1363564800,"individuals":260356},{"data_date":"2013-03-22","unix_timestamp":1363910400,"individuals":261635},{"data_date":"2013-04-05","unix_timestamp":1365120000,"individuals":293761},{"data_date":"2013-04-08","unix_timestamp":1365379200,"individuals":293761},{"data_date":"2013-04-17","unix_timestamp":1366156800,"individuals":291996},{"data_date":"2013-04-22","unix_timestamp":1366588800,"individuals":313232},{"data_date":"2013-04-23","unix_timestamp":1366675200,"individuals":313679},{"data_date":"2013-04-24","unix_timestamp":1366761600,"individuals":314337},{"data_date":"2013-04-25","unix_timestamp":1366848000,"individuals":313689},{"data_date":"2013-04-26","unix_timestamp":1366934400,"individuals":313872},{"data_date":"2013-04-29","unix_timestamp":1367193600,"individuals":316195},{"data_date":"2013-04-30","unix_timestamp":1367280000,"individuals":315923},{"data_date":"2013-05-01","unix_timestamp":1367366400,"individuals":316464},{"data_date":"2013-05-02","unix_timestamp":1367452800,"individuals":322609},{"data_date":"2013-05-03","unix_timestamp":1367539200,"individuals":322407},{"data_date":"2013-05-06","unix_timestamp":1367798400,"individuals":324770},{"data_date":"2013-05-07","unix_timestamp":1367884800,"individuals":322845},{"data_date":"2013-05-08","unix_timestamp":1367971200,"individuals":324731},{"data_date":"2013-05-09","unix_timestamp":1368057600,"individuals":325050},{"data_date":"2013-05-10","unix_timestamp":1368144000,"individuals":326555},{"data_date":"2013-05-13","unix_timestamp":1368403200,"individuals":329466},{"data_date":"2013-05-14","unix_timestamp":1368489600,"individuals":329714},{"data_date":"2013-05-15","unix_timestamp":1368576000,"individuals":347157},{"data_date":"2013-05-16","unix_timestamp":1368662400,"individuals":347157},{"data_date":"2013-05-17","unix_timestamp":1368748800,"individuals":347815},{"data_date":"2013-05-20","unix_timestamp":1369008000,"individuals":350736},{"data_date":"2013-05-21","unix_timestamp":1369094400,"individuals":350804},{"data_date":"2013-05-22","unix_timestamp":1369180800,"individuals":350991},{"data_date":"2013-05-23","unix_timestamp":1369267200,"individuals":350989},{"data_date":"2013-05-24","unix_timestamp":1369353600,"individuals":350797},{"data_date":"2013-05-27","unix_timestamp":1369612800,"individuals":376631},{"data_date":"2013-05-28","unix_timestamp":1369699200,"individuals":376884},{"data_date":"2013-05-29","unix_timestamp":1369785600,"individuals":377154},{"data_date":"2013-05-30","unix_timestamp":1369872000,"individuals":377154},{"data_date":"2013-05-31","unix_timestamp":1369958400,"individuals":372932},{"data_date":"2013-06-03","unix_timestamp":1370217600,"individuals":372326},{"data_date":"2013-06-05","unix_timestamp":1370390400,"individuals":381206},{"data_date":"2013-06-10","unix_timestamp":1370822400,"individuals":380420},{"data_date":"2013-06-11","unix_timestamp":1370908800,"individuals":380650},{"data_date":"2013-06-17","unix_timestamp":1371427200,"individuals":388935},{"data_date":"2013-06-18","unix_timestamp":1371513600,"individuals":388348},{"data_date":"2013-06-19","unix_timestamp":1371600000,"individuals":386927},{"data_date":"2013-06-20","unix_timestamp":1371686400,"individuals":387883},{"data_date":"2013-06-26","unix_timestamp":1372204800,"individuals":399736},{"data_date":"2013-07-04","unix_timestamp":1372896000,"individuals":398753},{"data_date":"2013-07-08","unix_timestamp":1373241600,"individuals":402189},{"data_date":"2013-07-09","unix_timestamp":1373328000,"individuals":402176},{"data_date":"2013-07-12","unix_timestamp":1373587200,"individuals":402163},{"data_date":"2013-07-15","unix_timestamp":1373846400,"individuals":412789},{"data_date":"2013-07-16","unix_timestamp":1373932800,"individuals":412789},{"data_date":"2013-07-17","unix_timestamp":1374019200,"individuals":413867},{"data_date":"2013-07-18","unix_timestamp":1374105600,"individuals":413867},{"data_date":"2013-07-19","unix_timestamp":1374192000,"individuals":413854},{"data_date":"2013-07-22","unix_timestamp":1374451200,"individuals":428198},{"data_date":"2013-07-23","unix_timestamp":1374537600,"individuals":428246},{"data_date":"2013-07-26","unix_timestamp":1374796800,"individuals":428227},{"data_date":"2013-07-30","unix_timestamp":1375142400,"individuals":431167},{"data_date":"2013-07-31","unix_timestamp":1375228800,"individuals":431081},{"data_date":"2013-08-05","unix_timestamp":1375660800,"individuals":434814},{"data_date":"2013-08-12","unix_timestamp":1376265600,"individuals":433971},{"data_date":"2013-08-14","unix_timestamp":1376438400,"individuals":434567},{"data_date":"2013-08-15","unix_timestamp":1376524800,"individuals":434576},{"data_date":"2013-08-19","unix_timestamp":1376870400,"individuals":440742},{"data_date":"2013-08-20","unix_timestamp":1376956800,"individuals":440757},{"data_date":"2013-08-21","unix_timestamp":1377043200,"individuals":440768},{"data_date":"2013-08-22","unix_timestamp":1377129600,"individuals":440773},{"data_date":"2013-08-27","unix_timestamp":1377561600,"individuals":458837},{"data_date":"2013-08-29","unix_timestamp":1377734400,"individuals":459207},{"data_date":"2013-09-02","unix_timestamp":1378080000,"individuals":463885},{"data_date":"2013-09-16","unix_timestamp":1379289600,"individuals":492687},{"data_date":"2013-09-17","unix_timestamp":1379376000,"individuals":492683},{"data_date":"2013-09-18","unix_timestamp":1379462400,"individuals":492709},{"data_date":"2013-09-19","unix_timestamp":1379548800,"individuals":492716},{"data_date":"2013-09-24","unix_timestamp":1379980800,"individuals":494330},{"data_date":"2013-09-26","unix_timestamp":1380153600,"individuals":494361},{"data_date":"2013-10-01","unix_timestamp":1380585600,"individuals":500237},{"data_date":"2013-10-04","unix_timestamp":1380844800,"individuals":500273},{"data_date":"2013-10-07","unix_timestamp":1381104000,"individuals":502827},{"data_date":"2013-10-09","unix_timestamp":1381276800,"individuals":502703},{"data_date":"2013-10-10","unix_timestamp":1381363200,"individuals":504415},{"data_date":"2013-10-11","unix_timestamp":1381449600,"individuals":504419},{"data_date":"2013-10-21","unix_timestamp":1382313600,"individuals":502737},{"data_date":"2013-10-22","unix_timestamp":1382400000,"individuals":502719},{"data_date":"2013-10-23","unix_timestamp":1382486400,"individuals":502743},{"data_date":"2013-10-24","unix_timestamp":1382572800,"individuals":502730},{"data_date":"2013-10-25","unix_timestamp":1382659200,"individuals":506530},{"data_date":"2013-10-29","unix_timestamp":1383004800,"individuals":506532},{"data_date":"2013-10-31","unix_timestamp":1383177600,"individuals":506551},{"data_date":"2013-11-02","unix_timestamp":1383350400,"individuals":510789},{"data_date":"2013-11-04","unix_timestamp":1383523200,"individuals":510826},{"data_date":"2013-11-05","unix_timestamp":1383609600,"individuals":512070},{"data_date":"2013-11-06","unix_timestamp":1383696000,"individuals":513157},{"data_date":"2013-11-07","unix_timestamp":1383782400,"individuals":513090},{"data_date":"2013-11-08","unix_timestamp":1383868800,"individuals":535993},{"data_date":"2013-11-11","unix_timestamp":1384128000,"individuals":516454},{"data_date":"2013-11-12","unix_timestamp":1384214400,"individuals":516383},{"data_date":"2013-11-15","unix_timestamp":1384473600,"individuals":516206},{"data_date":"2013-11-17","unix_timestamp":1384646400,"individuals":519938},{"data_date":"2013-11-19","unix_timestamp":1384819200,"individuals":521493},{"data_date":"2013-11-20","unix_timestamp":1384905600,"individuals":521493},{"data_date":"2013-11-21","unix_timestamp":1384992000,"individuals":522111},{"data_date":"2013-11-27","unix_timestamp":1385510400,"individuals":527223},{"data_date":"2013-11-28","unix_timestamp":1385596800,"individuals":527307},{"data_date":"2013-11-30","unix_timestamp":1385769600,"individuals":536371},{"data_date":"2013-12-03","unix_timestamp":1386028800,"individuals":536619},{"data_date":"2013-12-04","unix_timestamp":1386115200,"individuals":536663},{"data_date":"2013-12-05","unix_timestamp":1386201600,"individuals":536765},{"data_date":"2013-12-08","unix_timestamp":1386460800,"individuals":539681},{"data_date":"2013-12-09","unix_timestamp":1386547200,"individuals":539521},{"data_date":"2013-12-10","unix_timestamp":1386633600,"individuals":539796},{"data_date":"2013-12-11","unix_timestamp":1386720000,"individuals":540350},{"data_date":"2013-12-12","unix_timestamp":1386806400,"individuals":539761},{"data_date":"2013-12-16","unix_timestamp":1387152000,"individuals":553281},{"data_date":"2013-12-17","unix_timestamp":1387238400,"individuals":553151},{"data_date":"2013-12-18","unix_timestamp":1387324800,"individuals":553116},{"data_date":"2013-12-19","unix_timestamp":1387411200,"individuals":553508},{"data_date":"2013-12-22","unix_timestamp":1387670400,"individuals":554858},{"data_date":"2013-12-24","unix_timestamp":1387843200,"individuals":556094},{"data_date":"2013-12-25","unix_timestamp":1387929600,"individuals":557342},{"data_date":"2013-12-29","unix_timestamp":1388275200,"individuals":560428},{"data_date":"2013-12-31","unix_timestamp":1388448000,"individuals":560129},{"data_date":"2014-01-01","unix_timestamp":1388534400,"individuals":559994},{"data_date":"2014-01-05","unix_timestamp":1388880000,"individuals":565423},{"data_date":"2014-01-06","unix_timestamp":1388966400,"individuals":565444},{"data_date":"2014-01-07","unix_timestamp":1389052800,"individuals":565508},{"data_date":"2014-01-08","unix_timestamp":1389139200,"individuals":565776},{"data_date":"2014-01-09","unix_timestamp":1389225600,"individuals":566134},{"data_date":"2014-01-10","unix_timestamp":1389312000,"individuals":569199},{"data_date":"2014-01-12","unix_timestamp":1389484800,"individuals":571064},{"data_date":"2014-01-13","unix_timestamp":1389571200,"individuals":571513},{"data_date":"2014-01-14","unix_timestamp":1389657600,"individuals":571512},{"data_date":"2014-01-15","unix_timestamp":1389744000,"individuals":571684},{"data_date":"2014-01-16","unix_timestamp":1389830400,"individuals":571627},{"data_date":"2014-01-19","unix_timestamp":1390089600,"individuals":577313},{"data_date":"2014-01-20","unix_timestamp":1390176000,"individuals":577349},{"data_date":"2014-01-22","unix_timestamp":1390348800,"individuals":577936},{"data_date":"2014-01-23","unix_timestamp":1390435200,"individuals":577937},{"data_date":"2014-01-26","unix_timestamp":1390694400,"individuals":580119},{"data_date":"2014-01-27","unix_timestamp":1390780800,"individuals":580419},{"data_date":"2014-01-28","unix_timestamp":1390867200,"individuals":580542},{"data_date":"2014-01-29","unix_timestamp":1390953600,"individuals":580304},{"data_date":"2014-01-30","unix_timestamp":1391040000,"individuals":580756},{"data_date":"2014-02-02","unix_timestamp":1391299200,"individuals":593830},{"data_date":"2014-02-03","unix_timestamp":1391385600,"individuals":594397},{"data_date":"2014-02-04","unix_timestamp":1391472000,"individuals":594827},{"data_date":"2014-02-05","unix_timestamp":1391558400,"individuals":594854},{"data_date":"2014-02-06","unix_timestamp":1391644800,"individuals":595055},{"data_date":"2014-02-09","unix_timestamp":1391904000,"individuals":602662},{"data_date":"2014-02-10","unix_timestamp":1391990400,"individuals":602744},{"data_date":"2014-02-12","unix_timestamp":1392163200,"individuals":602739},{"data_date":"2014-02-13","unix_timestamp":1392249600,"individuals":603289},{"data_date":"2014-02-16","unix_timestamp":1392508800,"individuals":612502},{"data_date":"2014-02-17","unix_timestamp":1392595200,"individuals":612570},{"data_date":"2014-02-18","unix_timestamp":1392681600,"individuals":612535},{"data_date":"2014-02-19","unix_timestamp":1392768000,"individuals":612826},{"data_date":"2014-02-20","unix_timestamp":1392854400,"individuals":613393},{"data_date":"2014-02-23","unix_timestamp":1393113600,"individuals":619593},{"data_date":"2014-02-24","unix_timestamp":1393200000,"individuals":619642},{"data_date":"2014-02-25","unix_timestamp":1393286400,"individuals":619523},{"data_date":"2014-02-26","unix_timestamp":1393372800,"individuals":619356},{"data_date":"2014-02-27","unix_timestamp":1393459200,"individuals":619470},{"data_date":"2014-02-28","unix_timestamp":1393545600,"individuals":624308},{"data_date":"2014-03-02","unix_timestamp":1393718400,"individuals":624248},{"data_date":"2014-03-03","unix_timestamp":1393804800,"individuals":624415},{"data_date":"2014-03-04","unix_timestamp":1393891200,"individuals":624539},{"data_date":"2014-03-05","unix_timestamp":1393977600,"individuals":624666},{"data_date":"2014-03-06","unix_timestamp":1394064000,"individuals":624465},{"data_date":"2014-03-09","unix_timestamp":1394323200,"individuals":634344},{"data_date":"2014-03-10","unix_timestamp":1394409600,"individuals":634147},{"data_date":"2014-03-11","unix_timestamp":1394496000,"individuals":634901},{"data_date":"2014-03-12","unix_timestamp":1394582400,"individuals":634788},{"data_date":"2014-03-13","unix_timestamp":1394668800,"individuals":634882},{"data_date":"2014-03-16","unix_timestamp":1394928000,"individuals":642867},{"data_date":"2014-03-17","unix_timestamp":1395014400,"individuals":641771},{"data_date":"2014-03-18","unix_timestamp":1395100800,"individuals":641889},{"data_date":"2014-03-19","unix_timestamp":1395187200,"individuals":641906},{"data_date":"2014-03-20","unix_timestamp":1395273600,"individuals":642482},{"data_date":"2014-03-23","unix_timestamp":1395532800,"individuals":647379},{"data_date":"2014-03-24","unix_timestamp":1395619200,"individuals":647894},{"data_date":"2014-03-25","unix_timestamp":1395705600,"individuals":648909},{"data_date":"2014-03-26","unix_timestamp":1395792000,"individuals":649161},{"data_date":"2014-03-27","unix_timestamp":1395878400,"individuals":649302},{"data_date":"2014-03-30","unix_timestamp":1396137600,"individuals":667499},{"data_date":"2014-03-31","unix_timestamp":1396224000,"individuals":667496},{"data_date":"2014-04-01","unix_timestamp":1396310400,"individuals":667556},{"data_date":"2014-04-02","unix_timestamp":1396396800,"individuals":667636},{"data_date":"2014-04-03","unix_timestamp":1396483200,"individuals":667448},{"data_date":"2014-04-05","unix_timestamp":1396656000,"individuals":680377},{"data_date":"2014-04-06","unix_timestamp":1396742400,"individuals":679753},{"data_date":"2014-04-07","unix_timestamp":1396828800,"individuals":679910},{"data_date":"2014-04-08","unix_timestamp":1396915200,"individuals":679843},{"data_date":"2014-04-09","unix_timestamp":1397001600,"individuals":679697},{"data_date":"2014-04-13","unix_timestamp":1397347200,"individuals":713437},{"data_date":"2014-04-14","unix_timestamp":1397433600,"individuals":713092},{"data_date":"2014-04-15","unix_timestamp":1397520000,"individuals":712911},{"data_date":"2014-04-16","unix_timestamp":1397606400,"individuals":712555},{"data_date":"2014-04-20","unix_timestamp":1397952000,"individuals":715306},{"data_date":"2014-04-21","unix_timestamp":1398038400,"individuals":715215},{"data_date":"2014-04-23","unix_timestamp":1398211200,"individuals":714733},{"data_date":"2014-04-24","unix_timestamp":1398297600,"individuals":714552},{"data_date":"2014-04-25","unix_timestamp":1398384000,"individuals":722521},{"data_date":"2014-04-26","unix_timestamp":1398470400,"individuals":722055},{"data_date":"2014-04-28","unix_timestamp":1398643200,"individuals":722234},{"data_date":"2014-04-29","unix_timestamp":1398729600,"individuals":722216},{"data_date":"2014-04-30","unix_timestamp":1398816000,"individuals":735864},{"data_date":"2014-05-01","unix_timestamp":1398902400,"individuals":735618},{"data_date":"2014-05-04","unix_timestamp":1399161600,"individuals":735888},{"data_date":"2014-05-05","unix_timestamp":1399248000,"individuals":736040},{"data_date":"2014-05-06","unix_timestamp":1399334400,"individuals":736087},{"data_date":"2014-05-07","unix_timestamp":1399420800,"individuals":736137},{"data_date":"2014-05-08","unix_timestamp":1399507200,"individuals":736296},{"data_date":"2014-05-11","unix_timestamp":1399766400,"individuals":742816},{"data_date":"2014-05-12","unix_timestamp":1399852800,"individuals":743021},{"data_date":"2014-05-13","unix_timestamp":1399939200,"individuals":743277},{"data_date":"2014-05-15","unix_timestamp":1400112000,"individuals":743008},{"data_date":"2014-05-19","unix_timestamp":1400457600,"individuals":747735},{"data_date":"2014-05-20","unix_timestamp":1400544000,"individuals":748066},{"data_date":"2014-05-21","unix_timestamp":1400630400,"individuals":747909},{"data_date":"2014-05-22","unix_timestamp":1400716800,"individuals":747803},{"data_date":"2014-05-25","unix_timestamp":1400976000,"individuals":761779},{"data_date":"2014-05-26","unix_timestamp":1401062400,"individuals":761674},{"data_date":"2014-05-27","unix_timestamp":1401148800,"individuals":761206},{"data_date":"2014-05-28","unix_timestamp":1401235200,"individuals":761274},{"data_date":"2014-05-29","unix_timestamp":1401321600,"individuals":761297},{"data_date":"2014-05-31","unix_timestamp":1401494400,"individuals":761171},{"data_date":"2014-06-01","unix_timestamp":1401580800,"individuals":765560},{"data_date":"2014-06-02","unix_timestamp":1401667200,"individuals":765369},{"data_date":"2014-06-03","unix_timestamp":1401753600,"individuals":765113},{"data_date":"2014-06-04","unix_timestamp":1401840000,"individuals":764820},{"data_date":"2014-06-05","unix_timestamp":1401926400,"individuals":764798},{"data_date":"2014-06-08","unix_timestamp":1402185600,"individuals":774635},{"data_date":"2014-06-09","unix_timestamp":1402272000,"individuals":774252},{"data_date":"2014-06-10","unix_timestamp":1402358400,"individuals":774198},{"data_date":"2014-06-11","unix_timestamp":1402444800,"individuals":773864},{"data_date":"2014-06-12","unix_timestamp":1402531200,"individuals":773935},{"data_date":"2014-06-15","unix_timestamp":1402790400,"individuals":783163},{"data_date":"2014-06-17","unix_timestamp":1402963200,"individuals":783410},{"data_date":"2014-06-18","unix_timestamp":1403049600,"individuals":783044},{"data_date":"2014-06-19","unix_timestamp":1403136000,"individuals":783065},{"data_date":"2014-06-22","unix_timestamp":1403395200,"individuals":789469},{"data_date":"2014-06-23","unix_timestamp":1403481600,"individuals":789219},{"data_date":"2014-06-24","unix_timestamp":1403568000,"individuals":789613},{"data_date":"2014-06-25","unix_timestamp":1403654400,"individuals":789678},{"data_date":"2014-06-26","unix_timestamp":1403740800,"individuals":789750},{"data_date":"2014-06-29","unix_timestamp":1404000000,"individuals":795524},{"data_date":"2014-06-30","unix_timestamp":1404086400,"individuals":795442},{"data_date":"2014-07-01","unix_timestamp":1404172800,"individuals":795524},{"data_date":"2014-07-02","unix_timestamp":1404259200,"individuals":795726},{"data_date":"2014-07-03","unix_timestamp":1404345600,"individuals":795924},{"data_date":"2014-07-06","unix_timestamp":1404604800,"individuals":799291},{"data_date":"2014-07-07","unix_timestamp":1404691200,"individuals":799468},{"data_date":"2014-07-08","unix_timestamp":1404777600,"individuals":799521},{"data_date":"2014-07-09","unix_timestamp":1404864000,"individuals":799457},{"data_date":"2014-07-10","unix_timestamp":1404950400,"individuals":799410},{"data_date":"2014-07-13","unix_timestamp":1405209600,"individuals":805343},{"data_date":"2014-07-14","unix_timestamp":1405296000,"individuals":805308},{"data_date":"2014-07-15","unix_timestamp":1405382400,"individuals":805066},{"data_date":"2014-07-16","unix_timestamp":1405468800,"individuals":804602},{"data_date":"2014-07-17","unix_timestamp":1405555200,"individuals":804391},{"data_date":"2014-07-20","unix_timestamp":1405814400,"individuals":808931},{"data_date":"2014-07-21","unix_timestamp":1405900800,"individuals":808611},{"data_date":"2014-07-22","unix_timestamp":1405987200,"individuals":808589},{"data_date":"2014-07-23","unix_timestamp":1406073600,"individuals":808600},{"data_date":"2014-07-24","unix_timestamp":1406160000,"individuals":808576},{"data_date":"2014-07-29","unix_timestamp":1406592000,"individuals":813862},{"data_date":"2014-07-30","unix_timestamp":1406678400,"individuals":813860},{"data_date":"2014-07-31","unix_timestamp":1406764800,"individuals":815413},{"data_date":"2014-08-03","unix_timestamp":1407024000,"individuals":815065},{"data_date":"2014-08-04","unix_timestamp":1407110400,"individuals":815251},{"data_date":"2014-08-05","unix_timestamp":1407196800,"individuals":815088},{"data_date":"2014-08-06","unix_timestamp":1407283200,"individuals":814907},{"data_date":"2014-08-07","unix_timestamp":1407369600,"individuals":814212},{"data_date":"2014-08-10","unix_timestamp":1407628800,"individuals":822145},{"data_date":"2014-08-11","unix_timestamp":1407715200,"individuals":822499},{"data_date":"2014-08-12","unix_timestamp":1407801600,"individuals":822128},{"data_date":"2014-08-13","unix_timestamp":1407888000,"individuals":821635},{"data_date":"2014-08-14","unix_timestamp":1407974400,"individuals":822149},{"data_date":"2014-08-17","unix_timestamp":1408233600,"individuals":824454},{"data_date":"2014-08-18","unix_timestamp":1408320000,"individuals":824678},{"data_date":"2014-08-19","unix_timestamp":1408406400,"individuals":824766},{"data_date":"2014-08-20","unix_timestamp":1408492800,"individuals":824851},{"data_date":"2014-08-21","unix_timestamp":1408579200,"individuals":825012},{"data_date":"2014-08-22","unix_timestamp":1408665600,"individuals":831843},{"data_date":"2014-08-25","unix_timestamp":1408924800,"individuals":832508},{"data_date":"2014-09-02","unix_timestamp":1409616000,"individuals":840171},{"data_date":"2014-09-03","unix_timestamp":1409702400,"individuals":840009},{"data_date":"2014-09-04","unix_timestamp":1409788800,"individuals":840217},{"data_date":"2014-09-07","unix_timestamp":1410048000,"individuals":843779},{"data_date":"2014-09-08","unix_timestamp":1410134400,"individuals":844162},{"data_date":"2014-09-09","unix_timestamp":1410220800,"individuals":843728},{"data_date":"2014-09-10","unix_timestamp":1410307200,"individuals":843465},{"data_date":"2014-09-11","unix_timestamp":1410393600,"individuals":843625},{"data_date":"2014-09-14","unix_timestamp":1410652800,"individuals":847266},{"data_date":"2014-09-29","unix_timestamp":1411948800,"individuals":1029500},{"data_date":"2014-10-02","unix_timestamp":1412208000,"individuals":1065902},{"data_date":"2014-10-31","unix_timestamp":1414713600,"individuals":1097740},{"data_date":"2014-11-30","unix_timestamp":1417305600,"individuals":1165279},{"data_date":"2014-12-31","unix_timestamp":1419984000,"individuals":1622839},{"data_date":"2015-03-06","unix_timestamp":1425600000,"individuals":1698472},{"data_date":"2015-03-07","unix_timestamp":1425686400,"individuals":1698472},{"data_date":"2015-03-13","unix_timestamp":1426204800,"individuals":1718147},{"data_date":"2015-03-20","unix_timestamp":1426809600,"individuals":1738448},{"data_date":"2015-03-31","unix_timestamp":1427760000,"individuals":1741374},{"data_date":"2015-04-10","unix_timestamp":1428624000,"individuals":1758092},{"data_date":"2015-04-30","unix_timestamp":1430352000,"individuals":1759546},{"data_date":"2015-05-04","unix_timestamp":1430697600,"individuals":1759846},{"data_date":"2015-05-21","unix_timestamp":1432166400,"individuals":1761361},{"data_date":"2015-05-26","unix_timestamp":1432598400,"individuals":1761486},{"data_date":"2015-06-15","unix_timestamp":1434326400,"individuals":1772535},{"data_date":"2015-07-09","unix_timestamp":1436400000,"individuals":1805255},{"data_date":"2015-08-25","unix_timestamp":1440460800,"individuals":1938999},{"data_date":"2015-10-02","unix_timestamp":1443744000,"individuals":2072290},{"data_date":"2015-11-03","unix_timestamp":1446508800,"individuals":2181293},{"data_date":"2015-12-10","unix_timestamp":1449705600,"individuals":2291900},{"data_date":"2015-12-31","unix_timestamp":1451520000,"individuals":2503549},{"data_date":"2016-02-15","unix_timestamp":1455494400,"individuals":2620553},{"data_date":"2016-02-29","unix_timestamp":1456704000,"individuals":2688686},{"data_date":"2016-03-03","unix_timestamp":1456963200,"individuals":2715789},{"data_date":"2016-04-11","unix_timestamp":1460332800,"individuals":2749140},{"data_date":"2016-05-02","unix_timestamp":1462147200,"individuals":2749862},{"data_date":"2016-05-05","unix_timestamp":1462406400,"individuals":2748367},{"data_date":"2016-05-19","unix_timestamp":1463616000,"individuals":2744915},{"data_date":"2016-06-02","unix_timestamp":1464825600,"individuals":2743497},{"data_date":"2016-06-16","unix_timestamp":1466035200,"individuals":2739326},{"data_date":"2016-06-23","unix_timestamp":1466640000,"individuals":2733850},{"data_date":"2016-06-30","unix_timestamp":1467244800,"individuals":2733044},{"data_date":"2016-07-28","unix_timestamp":1469664000,"individuals":2728986},{"data_date":"2016-08-11","unix_timestamp":1470873600,"individuals":2724937},{"data_date":"2016-08-25","unix_timestamp":1472083200,"individuals":2726980},{"data_date":"2016-09-26","unix_timestamp":1474848000,"individuals":2733655},{"data_date":"2016-10-19","unix_timestamp":1476835200,"individuals":2753696},{"data_date":"2016-11-03","unix_timestamp":1478131200,"individuals":2764500},{"data_date":"2016-12-08","unix_timestamp":1481155200,"individuals":2790767},{"data_date":"2016-12-22","unix_timestamp":1482364800,"individuals":2814631},{"data_date":"2017-01-12","unix_timestamp":1484179200,"individuals":2854968},{"data_date":"2017-02-09","unix_timestamp":1486598400,"individuals":2896633},{"data_date":"2017-02-16","unix_timestamp":1487203200,"individuals":2910281},{"data_date":"2017-03-09","unix_timestamp":1489017600,"individuals":2957454},{"data_date":"2017-03-23","unix_timestamp":1490227200,"individuals":2967149},{"data_date":"2017-03-30","unix_timestamp":1490832000,"individuals":2969669},{"data_date":"2017-04-06","unix_timestamp":1491436800,"individuals":2973980},{"data_date":"2017-04-27","unix_timestamp":1493251200,"individuals":2992567},{"data_date":"2017-06-15","unix_timestamp":1497484800,"individuals":3049879},{"data_date":"2017-07-06","unix_timestamp":1499299200,"individuals":3079914},{"data_date":"2017-07-27","unix_timestamp":1501113600,"individuals":3106932},{"data_date":"2017-09-07","unix_timestamp":1504742400,"individuals":3168757},{"data_date":"2017-09-14","unix_timestamp":1505347200,"individuals":3184600},{"data_date":"2017-09-28","unix_timestamp":1506556800,"individuals":3181537},{"data_date":"2017-09-29","unix_timestamp":1506643200,"individuals":3208131},{"data_date":"2017-10-05","unix_timestamp":1507161600,"individuals":3222000},{"data_date":"2017-10-12","unix_timestamp":1507766400,"individuals":3235992},{"data_date":"2017-10-19","unix_timestamp":1508371200,"individuals":3251997},{"data_date":"2017-11-02","unix_timestamp":1509580800,"individuals":3285533},{"data_date":"2017-11-09","unix_timestamp":1510185600,"individuals":3303113},{"data_date":"2017-11-16","unix_timestamp":1510790400,"individuals":3320814},{"data_date":"2017-11-30","unix_timestamp":1512000000,"individuals":3359915},{"data_date":"2017-12-07","unix_timestamp":1512604800,"individuals":3381005},{"data_date":"2017-12-14","unix_timestamp":1513209600,"individuals":3400195},{"data_date":"2017-12-21","unix_timestamp":1513814400,"individuals":3412368},{"data_date":"2017-12-28","unix_timestamp":1514419200,"individuals":3424237},{"data_date":"2018-01-25","unix_timestamp":1516838400,"individuals":3466263},{"data_date":"2018-02-01","unix_timestamp":1517443200,"individuals":3485644},{"data_date":"2018-02-08","unix_timestamp":1518048000,"individuals":3506532},{"data_date":"2018-02-15","unix_timestamp":1518652800,"individuals":3523981},{"data_date":"2018-02-22","unix_timestamp":1519257600,"individuals":3531416},{"data_date":"2018-03-01","unix_timestamp":1519862400,"individuals":3540648},{"data_date":"2018-03-08","unix_timestamp":1520467200,"individuals":3547194},{"data_date":"2018-03-15","unix_timestamp":1521072000,"individuals":3554496},{"data_date":"2018-03-22","unix_timestamp":1521676800,"individuals":3561707},{"data_date":"2018-03-29","unix_timestamp":1522281600,"individuals":3567130},{"data_date":"2018-04-05","unix_timestamp":1522886400,"individuals":3572565},{"data_date":"2018-04-12","unix_timestamp":1523491200,"individuals":3578246},{"data_date":"2018-04-19","unix_timestamp":1524096000,"individuals":3584179},{"data_date":"2018-04-26","unix_timestamp":1524700800,"individuals":3588877},{"data_date":"2018-05-10","unix_timestamp":1525910400,"individuals":3586679},{"data_date":"2018-05-17","unix_timestamp":1526515200,"individuals":3593864},{"data_date":"2018-05-24","unix_timestamp":1527120000,"individuals":3589384},{"data_date":"2018-05-31","unix_timestamp":1527724800,"individuals":3583434},{"data_date":"2018-06-07","unix_timestamp":1528329600,"individuals":3579254},{"data_date":"2018-06-13","unix_timestamp":1528848000,"individuals":3576337},{"data_date":"2018-06-21","unix_timestamp":1529539200,"individuals":3570352},{"data_date":"2018-06-28","unix_timestamp":1530144000,"individuals":3562523},{"data_date":"2018-07-05","unix_timestamp":1530748800,"individuals":3554072},{"data_date":"2018-07-12","unix_timestamp":1531353600,"individuals":3546905},{"data_date":"2018-07-19","unix_timestamp":1531958400,"individuals":3541572},{"data_date":"2018-07-26","unix_timestamp":1532563200,"individuals":3533822},{"data_date":"2018-08-02","unix_timestamp":1533168000,"individuals":3542250},{"data_date":"2018-08-09","unix_timestamp":1533772800,"individuals":3545293},{"data_date":"2018-08-16","unix_timestamp":1534377600,"individuals":3548273},{"data_date":"2018-08-29","unix_timestamp":1535500800,"individuals":3552303},{"data_date":"2018-09-06","unix_timestamp":1536192000,"individuals":3555464},{"data_date":"2018-09-13","unix_timestamp":1536796800,"individuals":3559262},{"data_date":"2018-09-21","unix_timestamp":1537488000,"individuals":3564919},{"data_date":"2018-09-27","unix_timestamp":1538006400,"individuals":3567658},{"data_date":"2018-10-04","unix_timestamp":1538611200,"individuals":3577752},{"data_date":"2018-10-11","unix_timestamp":1539216000,"individuals":3585738},{"data_date":"2018-10-18","unix_timestamp":1539820800,"individuals":3587930},{"data_date":"2018-10-25","unix_timestamp":1540425600,"individuals":3589327},{"data_date":"2018-11-01","unix_timestamp":1541030400,"individuals":3596337},{"data_date":"2018-11-08","unix_timestamp":1541635200,"individuals":3594232},{"data_date":"2018-11-15","unix_timestamp":1542240000,"individuals":3597938},{"data_date":"2018-11-22","unix_timestamp":1542844800,"individuals":3603888},{"data_date":"2018-11-29","unix_timestamp":1543449600,"individuals":3607563},{"data_date":"2018-12-06","unix_timestamp":1544054400,"individuals":3598186},{"data_date":"2018-12-20","unix_timestamp":1545264000,"individuals":3618624},{"data_date":"2018-12-27","unix_timestamp":1545868800,"individuals":3622366},{"data_date":"2019-01-10","unix_timestamp":1547078400,"individuals":3628120},{"data_date":"2019-01-17","unix_timestamp":1547683200,"individuals":3632622},{"data_date":"2019-01-24","unix_timestamp":1548288000,"individuals":3636617},{"data_date":"2019-01-31","unix_timestamp":1548892800,"individuals":3640466},{"data_date":"2019-02-07","unix_timestamp":1549497600,"individuals":3644342},{"data_date":"2019-03-07","unix_timestamp":1551916800,"individuals":3642738},{"data_date":"2019-03-14","unix_timestamp":1552521600,"individuals":3646889},{"data_date":"2019-03-21","unix_timestamp":1553126400,"individuals":3651635},{"data_date":"2019-04-04","unix_timestamp":1554336000,"individuals":3630767},{"data_date":"2019-04-11","unix_timestamp":1554940800,"individuals":3621330},{"data_date":"2019-04-25","unix_timestamp":1556150400,"individuals":3605615},{"data_date":"2019-05-02","unix_timestamp":1556755200,"individuals":3603088},{"data_date":"2019-05-09","unix_timestamp":1557360000,"individuals":3606208},{"data_date":"2019-05-16","unix_timestamp":1557964800,"individuals":3606737},{"data_date":"2019-06-13","unix_timestamp":1560384000,"individuals":3614108},{"data_date":"2019-07-25","unix_timestamp":1564012800,"individuals":3639284},{"data_date":"2019-07-31","unix_timestamp":1564531200,"individuals":3643870},{"data_date":"2019-08-15","unix_timestamp":1565827200,"individuals":3649750},{"data_date":"2019-08-22","unix_timestamp":1566432000,"individuals":3654173},{"data_date":"2019-08-28","unix_timestamp":1566950400,"individuals":3657694},{"data_date":"2019-09-05","unix_timestamp":1567641600,"individuals":3658250},{"data_date":"2019-09-12","unix_timestamp":1568246400,"individuals":3663863},{"data_date":"2019-09-20","unix_timestamp":1568937600,"individuals":3666059},{"data_date":"2019-09-26","unix_timestamp":1569456000,"individuals":3667435},{"data_date":"2019-10-03","unix_timestamp":1570060800,"individuals":3671553},{"data_date":"2019-10-10","unix_timestamp":1570665600,"individuals":3674588},{"data_date":"2019-10-16","unix_timestamp":1571184000,"individuals":3676288},{"data_date":"2019-10-31","unix_timestamp":1572480000,"individuals":3680603},{"data_date":"2019-11-07","unix_timestamp":1573084800,"individuals":3682434},{"data_date":"2019-11-14","unix_timestamp":1573689600,"individuals":3684982},{"data_date":"2019-11-21","unix_timestamp":1574294400,"individuals":3687244},{"data_date":"2019-11-27","unix_timestamp":1574812800,"individuals":3691333},{"data_date":"2019-12-31","unix_timestamp":1577750400,"individuals":3576369},{"data_date":"2020-01-09","unix_timestamp":1578528000,"individuals":3576659}]